coinbase_commerce/__init__.py
coinbase_commerce/auth.py
coinbase_commerce/client.py
coinbase_commerce/compat.py
coinbase_commerce/error.py
coinbase_commerce/response.py
coinbase_commerce/util.py
coinbase_commerce/version.py
coinbase_commerce/webhook.py
coinbase_commerce/api_resources/__init__.py
coinbase_commerce/api_resources/charge.py
coinbase_commerce/api_resources/checkout.py
coinbase_commerce/api_resources/event.py
coinbase_commerce/api_resources/base/__init__.py
coinbase_commerce/api_resources/base/api_object.py
coinbase_commerce/api_resources/base/api_resource.py
coinbase_commerce/api_resources/base/create_api_resource.py
coinbase_commerce/api_resources/base/delete_api_resource.py
coinbase_commerce/api_resources/base/list_api_resource.py
coinbase_commerce/api_resources/base/update_api_resource.py
coinbase_commerce-1.0.1.dist-info/LICENSE.txt
coinbase_commerce-1.0.1.dist-info/METADATA
coinbase_commerce-1.0.1.dist-info/RECORD
coinbase_commerce-1.0.1.dist-info/WHEEL
coinbase_commerce-1.0.1.dist-info/top_level.txt
