Metadata-Version: 2.1
Name: coinbase-commerce
Version: 1.0.1
Summary: Coinbase Commerce API client library
Home-page: https://github.com/coinbase/coinbase-commerce-python
Author: Coinbase, Inc.
License: Apache 2.0
Keywords: api,coinbase commerce,client
Platform: UNKNOWN
Classifier: Intended Audience :: Developers
Classifier: License :: OSI Approved :: MIT License
Classifier: Operating System :: OS Independent
Classifier: Programming Language :: Python :: 2
Classifier: Programming Language :: Python :: 2.7
Classifier: Programming Language :: Python :: 3
Classifier: Programming Language :: Python :: 3.4
Classifier: Programming Language :: Python :: 3.5
Classifier: Programming Language :: Python :: 3.6
Classifier: Programming Language :: Python :: 3.7
Classifier: Programming Language :: Python
Classifier: Intended Audience :: Developers
Classifier: Topic :: Software Development :: Libraries :: Python Modules
